{
  "parent": "unsortedcannibals:root",
  "display": {
    "icon": {
      "item": "unsortedcannibals:visceral_pain"
    },
    "title": {
      "translate" : "title.unsortedcannibals.visceral_pain"
    },
    "description": {
      "translate": "description.unsortedcannibals.visceral_pain"
    },
    "frame": "goal",
    "announce_to_chat": true,
    "hidden": true
  },
  "criteria": {
    "requirement": {
      "trigger": "minecraft:effects_changed",
      "conditions": {
        "effects": {
          "unsortedcannibals:visceral_pain": {}
        }
      }
    }
  }
}